forfloatrange.py
forfloatrange-1.2.1.dist-info/METADATA
forfloatrange-1.2.1.dist-info/WHEEL
forfloatrange-1.2.1.dist-info/RECORD
